pygalaxy/__init__.py
pygalaxy/ConsistentHash/__init__.py
pygalaxy/ConvertMaster/__init__.py
pygalaxy/DecimalMaster/__init__.py
pygalaxy/HttpMaster/__init__.py
pygalaxy/TimeMaster/__init__.py
pygalaxy/config/__init__.py
pygalaxy/logger/__init__.py
pygalaxy/security/__init__.py
pygalaxy/sql_master/__init__.py
pygalaxy-0.4.2.dist-info/LICENSE
pygalaxy-0.4.2.dist-info/METADATA
pygalaxy-0.4.2.dist-info/WHEEL
pygalaxy-0.4.2.dist-info/top_level.txt
pygalaxy-0.4.2.dist-info/RECORD
