Metadata-Version: 2.1
Name: pygalaxy
Version: 0.4.2
Summary: common package
Home-page: https://github.com/patrickxu1986/pygalaxy
Author: patrickxu
Author-email: xcpxcp198608@163.com
Project-URL: Bug Tracker, https://github.com/patrickxu1986/pygalaxy/issues
Classifier: Programming Language :: Python :: 3
Classifier: License :: OSI Approved :: MIT License
Classifier: Operating System :: OS Independent
Requires-Python: >=3.6
License-File: LICENSE
Requires-Dist: pycryptodome (>=3.15.0)
Requires-Dist: pymysql (>=1.0.2)
Requires-Dist: PyJWT (>=2.6.0)
Requires-Dist: requests (>=2.28.1)
Requires-Dist: numpy (>=1.23.4)
Requires-Dist: beautifulsoup4 (>=4.11.1)
